phonikud_tts/__init__.py
phonikud_tts/py.typed
phonikud_tts-0.1.3.dist-info/METADATA
phonikud_tts-0.1.3.dist-info/WHEEL
phonikud_tts-0.1.3.dist-info/RECORD
