Metadata-Version: 2.4
Name: phonikud-tts
Version: 0.1.3
Summary: Add your description here
Author-email: thewh1teagle <61390950+thewh1teagle@users.noreply.github.com>
Requires-Python: >=3.11
Requires-Dist: phonikud
Requires-Dist: phonikud-onnx>=1.0.3
Requires-Dist: piper-onnx>=1.0.5
Requires-Dist: sounddevice>=0.5.2
Requires-Dist: soundfile>=0.13.1
